forecastdrift/__init__.py
forecastdrift/alarm.py
forecastdrift/tools.py
forecastdrift/views_forecast_drift.py
forecastdrift-0.2.1.dist-info/METADATA
forecastdrift-0.2.1.dist-info/WHEEL
forecastdrift-0.2.1.dist-info/RECORD
